src/running-tools/__init__.py
src/running-tools/__main__.py
src/running-tools/running-tools.py
running_tools-0.0.1.dist-info/LICENSE
running_tools-0.0.1.dist-info/WHEEL
running_tools-0.0.1.dist-info/METADATA
running_tools-0.0.1.dist-info/RECORD
